dataclasses_reverse_cli/__init__.py
dataclasses_reverse_cli/reverse_cli.py
dataclasses_reverse_cli-0.0.7.dist-info/METADATA
dataclasses_reverse_cli-0.0.7.dist-info/WHEEL
dataclasses_reverse_cli-0.0.7.dist-info/licenses/LICENSE.md
dataclasses_reverse_cli-0.0.7.dist-info/RECORD
