Metadata-Version: 2.4
Name: dataclasses-reverse-cli
Version: 0.0.7
Summary: Dataclass to be CLI and logger compatible
Project-URL: Repository, https://codeberg.org/MalcolmMielle/dataclasses-reverse-cli
Project-URL: Issues, https://codeberg.org/MalcolmMielle/dataclasses-reverse-cli/issues
License: AGPL-3.0-or-later
License-File: LICENSE.md
Keywords: cli,dataclass,logging
Requires-Python: >=3.10
Requires-Dist: deprecated>=1.2.18
